[
    {
        "line": 18
    },
    {
        "main": {
            "c": {
                "cor": "vermelho",
                "rodas": 4,
                "_velocidade": 0,
                "_aceleracao": 0,
                "_freio": 0
            }
        },
        "line": 12
    },
    {
        "main": {
            "c": {
                "cor": "vermelho",
                "rodas": 4,
                "_velocidade": 10,
                "_aceleracao": 10,
                "_freio": 0
            },
            "acelerar": {
                "self": {
                    "cor": "vermelho",
                    "rodas": 4,
                    "_velocidade": 10,
                    "_aceleracao": 10,
                    "_freio": 0
                },
                "aceleracao": 10
            }
        },
        "line": null
    }
]